<?xml version="1.0" encoding="UTF-8"?>

<!--Cái Question đầu tiên là mẫu, anh đừng điền hay xóa nhé.
    Anh tìm câu hỏi và câu trả lời từ Quiz ở W3School nhé.
    Anh nhớ kiểm tra câu trả lời đúng và cho vào phần correct trong <Answer> nhé 

    level_id: (ID Độ khó) type: int
    type_id: (ID Loại câu hỏi) type: int
    subject_ID (ID Môn) type: string
    scrambled: (Có đảo đáp án hay ko (true/false)) type: boolean
    chapter: (Chương) type: int
-->

<Questions>
    <Question id="1" level_id="1" type_id="1" subject_id="1" scrambled="true" chapter="1">
        <Content>What does HTML stand for?</Content>
        <Answer correct="true">Hyper Text Markup Language</Answer>
        <Answer correct="false">Home Tool Markup Language</Answer>
        <Answer correct="false">Hyperlinks and Text Markup Language</Answer>
    </Question>
    
    <Question id="2" level_id="2" type_id="1" subject_id="1" scrambled="true" chapter="1">
        <Content>Who is making the Web standards?</Content>
        <Answer correct="true">The World Wide Web Consortium</Answer>
        <Answer correct="false">Mozilla</Answer>
        <Answer correct="false">Microsoft</Answer>
        <Answer correct="false">Google</Answer>
    </Question>
    
    <Question id="3" level_id="2" type_id="1" subject_id="1" scrambled="true" chapter="1">
        <Content>In HTML, inline elements are normally displayed without starting a new line</Content>
        <Answer correct="true">True</Answer>
        <Answer correct="false">False</Answer>
    </Question>
    
    <Question id="4" level_id="1" type_id="1" subject_id="1" scrambled="true" chapter="">
        <Content></Content>
        <Answer correct="true"></Answer>
        <Answer correct="false"></Answer>
        <Answer correct="false"></Answer>
        <Answer correct="false"></Answer>
    </Question>
    
    <Question id="5" level_id="1" type_id="1" subject_id="1" scrambled="true" chapter="">
        <Content></Content>
        <Answer correct="true"></Answer>
        <Answer correct="false"></Answer>
        <Answer correct="false"></Answer>
        <Answer correct="false"></Answer>
    </Question>
    
    <Question id="6" level_id="1" type_id="1" subject_id="1" scrambled="true" chapter="">
        <Content></Content>
        <Answer correct="true"></Answer>
        <Answer correct="false"></Answer>
        <Answer correct="false"></Answer>
        <Answer correct="false"></Answer>
    </Question>
    
    <Question id="7" level_id="1" type_id="1" subject_id="1" scrambled="true" chapter="">
        <Content></Content>
        <Answer correct="true"></Answer>
        <Answer correct="false"></Answer>
        <Answer correct="false"></Answer>
        <Answer correct="false"></Answer>
    </Question>
    
    <Question id="8" level_id="1" type_id="1" subject_id="1" scrambled="true" chapter="">
        <Content></Content>
        <Answer correct="true"></Answer>
        <Answer correct="false"></Answer>
        <Answer correct="false"></Answer>
        <Answer correct="false"></Answer>
    </Question>
    
    <Question id="9" level_id="1" type_id="1" subject_id="1" scrambled="true" chapter="">
        <Content></Content>
        <Answer correct="true"></Answer>
        <Answer correct="false"></Answer>
        <Answer correct="false"></Answer>
        <Answer correct="false"></Answer>
    </Question>
    
    <Question id="10" level_id="1" type_id="1" subject_id="1" scrambled="true" chapter="">
        <Content></Content>
        <Answer correct="true"></Answer>
        <Answer correct="false"></Answer>
        <Answer correct="false"></Answer>
        <Answer correct="false"></Answer>
    </Question>
    
    <Question id="11" level_id="1" type_id="1" subject_id="1" scrambled="true" chapter="">
        <Content></Content>
        <Answer correct="true"></Answer>
        <Answer correct="false"></Answer>
        <Answer correct="false"></Answer>
        <Answer correct="false"></Answer>
    </Question>
    
    <Question id="12" level_id="1" type_id="1" subject_id="1" scrambled="true" chapter="">
        <Content></Content>
        <Answer correct="true"></Answer>
        <Answer correct="false"></Answer>
        <Answer correct="false"></Answer>
        <Answer correct="false"></Answer>
    </Question>
    
    <Question id="13" level_id="1" type_id="1" subject_id="1" scrambled="true" chapter="">
        <Content></Content>
        <Answer correct="true"></Answer>
        <Answer correct="false"></Answer>
        <Answer correct="false"></Answer>
        <Answer correct="false"></Answer>
    </Question>
    
    <Question id="14" level_id="1" type_id="1" subject_id="1" scrambled="true" chapter="">
        <Content></Content>
        <Answer correct="true"></Answer>
        <Answer correct="false"></Answer>
        <Answer correct="false"></Answer>
        <Answer correct="false"></Answer>
    </Question>
    
    <Question id="15" level_id="1" type_id="1" subject_id="1" scrambled="true" chapter="">
        <Content></Content>
        <Answer correct="true"></Answer>
        <Answer correct="false"></Answer>
        <Answer correct="false"></Answer>
        <Answer correct="false"></Answer>
    </Question>
    
    <Question id="16" level_id="1" type_id="1" subject_id="1" scrambled="true" chapter="">
        <Content></Content>
        <Answer correct="true"></Answer>
        <Answer correct="false"></Answer>
        <Answer correct="false"></Answer>
        <Answer correct="false"></Answer>
    </Question>
    
    <Question id="17" level_id="1" type_id="1" subject_id="1" scrambled="true" chapter="">
        <Content></Content>
        <Answer correct="true"></Answer>
        <Answer correct="false"></Answer>
        <Answer correct="false"></Answer>
        <Answer correct="false"></Answer>
    </Question>
    
    <Question id="18" level_id="1" type_id="1" subject_id="1" scrambled="true" chapter="">
        <Content></Content>
        <Answer correct="true"></Answer>
        <Answer correct="false"></Answer>
        <Answer correct="false"></Answer>
        <Answer correct="false"></Answer>
    </Question>
    
    <Question id="19" level_id="1" type_id="1" subject_id="1" scrambled="true" chapter="">
        <Content></Content>
        <Answer correct="true"></Answer>
        <Answer correct="false"></Answer>
        <Answer correct="false"></Answer>
        <Answer correct="false"></Answer>
    </Question>
    
    <Question id="20" level_id="1" type_id="1" subject_id="1" scrambled="true" chapter="">
        <Content></Content>
        <Answer correct="true"></Answer>
        <Answer correct="false"></Answer>
        <Answer correct="false"></Answer>
        <Answer correct="false"></Answer>
    </Question>
    
    <Question id="21" level_id="2" type_id="1" subject_id="2" scrambled="true" chapter="1">
        <Content>What does CSS stand for?</Content>
        <Answer correct="true">Cascading Style Sheets</Answer>
        <Answer correct="false">Computer Style Sheets</Answer>
        <Answer correct="false">Colorful Style Sheets</Answer>
        <Answer correct="false">Creative Style Sheets</Answer>
    </Question>
    
    <Question id="22" level_id="1" type_id="1" subject_id="2" scrambled="true" chapter="2">
        <Content>Which HTML attribute is used to define inline styles?</Content>
        <Answer correct="true">style</Answer>
        <Answer correct="false">class</Answer>
        <Answer correct="false">styles</Answer>
        <Answer correct="false">font</Answer>
    </Question>
    
    <Question id="23" level_id="1" type_id="1" subject_id="2" scrambled="true" chapter="5">
        <Content>Which is the correct CSS syntax?</Content>
        <Answer correct="true">body {color: black;}</Answer>
        <Answer correct="false">{body:color=black;}</Answer>
        <Answer correct="false">{body;color:black;}</Answer>
        <Answer correct="false">body:color=black;</Answer>
    </Question>
    
    <Question id="24" level_id="1" type_id="1" subject_id="2" scrambled="true" chapter="3">
        <Content>How do you insert a comment in a CSS file?</Content>
        <Answer correct="true">/* this is a comment */</Answer>
        <Answer correct="false">// this is a comment //</Answer>
        <Answer correct="false">// this is a comment</Answer>
        <Answer correct="false">' this is a comment</Answer>
    </Question>
    
    <Question id="25" level_id="1" type_id="1" subject_id="2" scrambled="true" chapter="7">
        <Content>Which property is used to change the background color?</Content>
        <Answer correct="true">background-color</Answer>
        <Answer correct="false">bgcolor</Answer>
        <Answer correct="false">color</Answer>
    </Question>
    
    <Question id="26" level_id="1" type_id="1" subject_id="2" scrambled="true" chapter="8">
        <Content>Which CSS property is used to change the text color of an element?</Content>
        <Answer correct="true">color</Answer>
        <Answer correct="false">fgcolor</Answer>
        <Answer correct="false">text-color</Answer>
    </Question>
    
    <Question id="27" level_id="1" type_id="1" subject_id="2" scrambled="true" chapter="2">
        <Content>Which CSS property controls the text size?</Content>
        <Answer correct="true">font-size</Answer>
        <Answer correct="false">font-style</Answer>
        <Answer correct="false">text-style</Answer>
        <Answer correct="false">text-size</Answer>
    </Question>
    
    <Question id="28" level_id="1" type_id="1" subject_id="2" scrambled="true" chapter="4">
        <Content>How do you display hyperlinks without an underline?</Content>
        <Answer correct="true">a {text-decoration:none;}</Answer>
        <Answer correct="false">a {text-decoration:no-underline;}</Answer>
        <Answer correct="false">a {decoration:no-underline;}</Answer>
        <Answer correct="false">a {underline:none;}</Answer>
    </Question>
    
    <Question id="29" level_id="1" type_id="1" subject_id="2" scrambled="true" chapter="3">
        <Content>How do you make each word in a text start with a capital letter?</Content>
        <Answer correct="true">text-transform:capitalize</Answer>
        <Answer correct="false">You can't do that with CSS</Answer>
        <Answer correct="false">text-transform:uppercase</Answer>
    </Question>
    
    <Question id="30" level_id="1" type_id="1" subject_id="2" scrambled="true" chapter="7">
        <Content>Which property is used to change the font of an element?</Content>
        <Answer correct="true">Both font-family and font can be used</Answer>
        <Answer correct="false">font</Answer>
        <Answer correct="false">font-family</Answer>
    </Question>
    
    <Question id="31" level_id="1" type_id="1" subject_id="2" scrambled="true" chapter="5">
        <Content>How do you make the text bold?</Content>
        <Answer correct="true">font-weight:bold;</Answer>
        <Answer correct="false">font:bold;</Answer>
        <Answer correct="false">style:bold;</Answer>
        
    </Question>
    
    <Question id="32" level_id="1" type_id="1" subject_id="2" scrambled="true" chapter="6">
        <Content>How do you display a border like this:
            The top border = 10 pixels 
            The bottom border = 5 pixels
            The left border = 20 pixels
            The right border = 1 pixel?</Content>
        <Answer correct="true">border-width:10px 1px 5px 20px;</Answer>
        <Answer correct="false">border-width:10px 5px 20px 1px;</Answer>
        <Answer correct="false">border-width:5px 20px 10px 1px;</Answer>
        <Answer correct="false">border-width:10px 20px 5px 1px;</Answer>
    </Question>
    
    <Question id="33" level_id="1" type_id="1" subject_id="2" scrambled="true" chapter="6">
        <Content>Which property is used to change the left margin of an element?</Content>
        <Answer correct="true">margin-left</Answer>
        <Answer correct="false">padding-left</Answer>
        <Answer correct="false">indent</Answer>
    </Question>
    
    <Question id="34" level_id="1" type_id="1" subject_id="2" scrambled="true" chapter="1">
        <Content> When using the padding property, are you allowed to use negative values?</Content>
        <Answer correct="true">No</Answer>
        <Answer correct="false">Yes</Answer>
    </Question>
    
    <Question id="35" level_id="1" type_id="1" subject_id="2" scrambled="true" chapter="4">
        <Content>How do you make a list that lists its items with squares?</Content>
        <Answer correct="true">list-style-type: square;</Answer>
        <Answer correct="false">list-type: square;</Answer>
        <Answer correct="false">list: square;</Answer>
    </Question>
    
    <Question id="36" level_id="1" type_id="1" subject_id="2" scrambled="true" chapter="">
        <Content></Content>
        <Answer correct="true"></Answer>
        <Answer correct="false"></Answer>
        <Answer correct="false"></Answer>
        <Answer correct="false"></Answer>
    </Question>
    
    <Question id="37" level_id="1" type_id="1" subject_id="2" scrambled="true" chapter="">
        <Content></Content>
        <Answer correct="true"></Answer>
        <Answer correct="false"></Answer>
        <Answer correct="false"></Answer>
        <Answer correct="false"></Answer>
    </Question>
    
    <Question id="38" level_id="1" type_id="1" subject_id="2" scrambled="true" chapter="">
        <Content></Content>
        <Answer correct="true"></Answer>
        <Answer correct="false"></Answer>
        <Answer correct="false"></Answer>
        <Answer correct="false"></Answer>
    </Question>
    
    <Question id="39" level_id="1" type_id="1" subject_id="2" scrambled="true" chapter="">
        <Content></Content>
        <Answer correct="true"></Answer>
        <Answer correct="false"></Answer>
        <Answer correct="false"></Answer>
        <Answer correct="false"></Answer>
    </Question>
    
    <Question id="40" level_id="1" type_id="1" subject_id="2" scrambled="true" chapter="">
        <Content></Content>
        <Answer correct="true"></Answer>
        <Answer correct="false"></Answer>
        <Answer correct="false"></Answer>
        <Answer correct="false"></Answer>
    </Question>
    
    <Question id="41" level_id="1" type_id="1" subject_id="3" scrambled="true" chapter="1">
        <Content>What is the previous version of HTML, prior to HTML5?</Content>
        <Answer correct="true">HTML 4.01</Answer>
        <Answer correct="false">HTML 4.1</Answer>
        <Answer correct="false">HTML 4</Answer>
        <Answer correct="false">HTML 4.9</Answer>
    </Question>
    
    <Question id="42" level_id="1" type_id="1" subject_id="3" scrambled="true" chapter="3">
        <Content>In HTML5, onblur and onfocus are:</Content>
        <Answer correct="true"></Answer>
        <Answer correct="false"></Answer>
        <Answer correct="false"></Answer>
        <Answer correct="false"></Answer>
    </Question>
    
    <Question id="43" level_id="1" type_id="1" subject_id="3" scrambled="true" chapter="">
        <Content></Content>
        <Answer correct="true"></Answer>
        <Answer correct="false"></Answer>
        <Answer correct="false"></Answer>
        <Answer correct="false"></Answer>
    </Question>
    
    <Question id="44" level_id="1" type_id="1" subject_id="3" scrambled="true" chapter="">
        <Content></Content>
        <Answer correct="true"></Answer>
        <Answer correct="false"></Answer>
        <Answer correct="false"></Answer>
        <Answer correct="false"></Answer>
    </Question>
    
    <Question id="45" level_id="1" type_id="1" subject_id="3" scrambled="true" chapter="">
        <Content></Content>
        <Answer correct="true"></Answer>
        <Answer correct="false"></Answer>
        <Answer correct="false"></Answer>
        <Answer correct="false"></Answer>
    </Question>
    
    <Question id="46" level_id="1" type_id="1" subject_id="3" scrambled="true" chapter="">
        <Content></Content>
        <Answer correct="true"></Answer>
        <Answer correct="false"></Answer>
        <Answer correct="false"></Answer>
        <Answer correct="false"></Answer>
    </Question>
    
    <Question id="47" level_id="1" type_id="1" subject_id="3" scrambled="true" chapter="">
        <Content></Content>
        <Answer correct="true"></Answer>
        <Answer correct="false"></Answer>
        <Answer correct="false"></Answer>
        <Answer correct="false"></Answer>
    </Question>
    
    <Question id="48" level_id="1" type_id="1" subject_id="3" scrambled="true" chapter="">
        <Content></Content>
        <Answer correct="true"></Answer>
        <Answer correct="false"></Answer>
        <Answer correct="false"></Answer>
        <Answer correct="false"></Answer>
    </Question>
    
    <Question id="49" level_id="1" type_id="1" subject_id="3" scrambled="true" chapter="">
        <Content></Content>
        <Answer correct="true"></Answer>
        <Answer correct="false"></Answer>
        <Answer correct="false"></Answer>
        <Answer correct="false"></Answer>
    </Question>
    
    <Question id="50" level_id="1" type_id="1" subject_id="3" scrambled="true" chapter="">
        <Content></Content>
        <Answer correct="true"></Answer>
        <Answer correct="false"></Answer>
        <Answer correct="false"></Answer>
        <Answer correct="false"></Answer>
    </Question>
    
    <Question id="51" level_id="1" type_id="1" subject_id="3" scrambled="true" chapter="">
        <Content></Content>
        <Answer correct="true"></Answer>
        <Answer correct="false"></Answer>
        <Answer correct="false"></Answer>
        <Answer correct="false"></Answer>
    </Question>
    
    <Question id="52" level_id="1" type_id="1" subject_id="3" scrambled="true" chapter="">
        <Content></Content>
        <Answer correct="true"></Answer>
        <Answer correct="false"></Answer>
        <Answer correct="false"></Answer>
        <Answer correct="false"></Answer>
    </Question>
    
    <Question id="53" level_id="1" type_id="1" subject_id="3" scrambled="true" chapter="">
        <Content></Content>
        <Answer correct="true"></Answer>
        <Answer correct="false"></Answer>
        <Answer correct="false"></Answer>
        <Answer correct="false"></Answer>
    </Question>
    
    <Question id="54" level_id="1" type_id="1" subject_id="3" scrambled="true" chapter="">
        <Content></Content>
        <Answer correct="true"></Answer>
        <Answer correct="false"></Answer>
        <Answer correct="false"></Answer>
        <Answer correct="false"></Answer>
    </Question>
    
    <Question id="55" level_id="1" type_id="1" subject_id="3" scrambled="true" chapter="">
        <Content></Content>
        <Answer correct="true"></Answer>
        <Answer correct="false"></Answer>
        <Answer correct="false"></Answer>
        <Answer correct="false"></Answer>
    </Question>
    
    <Question id="56" level_id="1" type_id="1" subject_id="3" scrambled="true" chapter="">
        <Content></Content>
        <Answer correct="true"></Answer>
        <Answer correct="false"></Answer>
        <Answer correct="false"></Answer>
        <Answer correct="false"></Answer>
    </Question>
    
    <Question id="57" level_id="1" type_id="1" subject_id="3" scrambled="true" chapter="">
        <Content></Content>
        <Answer correct="true"></Answer>
        <Answer correct="false"></Answer>
        <Answer correct="false"></Answer>
        <Answer correct="false"></Answer>
    </Question>
    
    <Question id="58" level_id="1" type_id="1" subject_id="3" scrambled="true" chapter="">
        <Content></Content>
        <Answer correct="true"></Answer>
        <Answer correct="false"></Answer>
        <Answer correct="false"></Answer>
        <Answer correct="false"></Answer>
    </Question>
    
    <Question id="59" level_id="1" type_id="1" subject_id="3" scrambled="true" chapter="">
        <Content></Content>
        <Answer correct="true"></Answer>
        <Answer correct="false"></Answer>
        <Answer correct="false"></Answer>
        <Answer correct="false"></Answer>
    </Question>
    
    <Question id="60" level_id="1" type_id="1" subject_id="3" scrambled="true" chapter="">
        <Content></Content>
        <Answer correct="true"></Answer>
        <Answer correct="false"></Answer>
        <Answer correct="false"></Answer>
        <Answer correct="false"></Answer>
    </Question>
    
    <Question id="61" level_id="1" type_id="1" subject_id="4" scrambled="true" chapter="">
        <Content>How do you write "Hello World" in an alert box?</Content>
        <Answer correct="true">alert("Hello World");</Answer>
        <Answer correct="false">msg("Hello World");</Answer>
        <Answer correct="false">msgBox("Hello World");</Answer>
        <Answer correct="false">alertBox("Hello World");</Answer>
    </Question>
    
    <Question id="62" level_id="1" type_id="1" subject_id="4" scrambled="true" chapter="">
        <Content>How do you create a function in JavaScript?</Content>
        <Answer correct="true">function = myFunction()</Answer>
        <Answer correct="false">function:myFunction()</Answer>
        <Answer correct="false">function myFunction()</Answer>
    </Question>
    
    <Question id="63" level_id="1" type_id="1" subject_id="4" scrambled="true" chapter="">
        <Content>How do you call a function named "myFunction"?</Content>
        <Answer correct="true">myFunction()</Answer>
        <Answer correct="false">call myFunction()</Answer>
        <Answer correct="false">call function myFunction()</Answer>
    </Question>
    
    <Question id="64" level_id="1" type_id="1" subject_id="4" scrambled="true" chapter="">
        <Content>How to write an IF statement in JavaScript?</Content>
        <Answer correct="true">if (i == 5)</Answer>
        <Answer correct="false">if i = 5 then</Answer>
        <Answer correct="false">if i = 5</Answer>
        <Answer correct="false">if i == 5 then</Answer>
    </Question>
    
    <Question id="65" level_id="1" type_id="1" subject_id="4" scrambled="true" chapter="">
        <Content>What is the correct way to write a JavaScript array?</Content>
        <Answer correct="true">var colors = (1:"red", 2:"green", 3:"blue")</Answer>
        <Answer correct="false">var colors = ["red", "green", "blue"]</Answer>
        <Answer correct="false">var colors = 1 = ("red"), 2 = ("green"), 3 = ("blue")</Answer>
        <Answer correct="false">var colors = "red", "green", "blue"</Answer>
    </Question>
    
    <Question id="66" level_id="1" type_id="1" subject_id="4" scrambled="true" chapter="">
        <Content>How do you round the number 7.25, to the nearest integer?</Content>
        <Answer correct="true">round(7.25)</Answer>
        <Answer correct="false">Math.round(7.25)</Answer>
        <Answer correct="false">Math.rnd(7.25)</Answer>
        <Answer correct="false">rnd(7.25)</Answer>
    </Question>
    
    <Question id="67" level_id="1" type_id="1" subject_id="4" scrambled="true" chapter="">
        <Content>How do you find the number with the highest value of x and y?</Content>
        <Answer correct="true">Math.max(x, y)</Answer>
        <Answer correct="false">top(x, y)</Answer>
        <Answer correct="false">Math.ceil(x, y)</Answer>
        <Answer correct="false">ceil(x, y)</Answer>
    </Question>
    
    <Question id="68" level_id="1" type_id="1" subject_id="4" scrambled="true" chapter="">
        <Content>What is the correct JavaScript syntax for opening a new window called "w2" ?</Content>
        <Answer correct="true">w2 = window.open("http://www.w3schools.com");</Answer>
        <Answer correct="false">w2 = window.new("http://www.w3schools.com");</Answer>
    </Question>
    
    <Question id="69" level_id="1" type_id="1" subject_id="4" scrambled="true" chapter="">
        <Content>JavaScript is the same as Java</Content>
        <Answer correct="true">False</Answer>
        <Answer correct="false">True</Answer>
    </Question>
    
    <Question id="70" level_id="1" type_id="1" subject_id="4" scrambled="true" chapter="">
        <Content>How can you detect the client's browser name?</Content>
        <Answer correct="true">navigator.appName</Answer>
        <Answer correct="false">browser.name</Answer>
        <Answer correct="false">client.navName</Answer>
    </Question>
    
    <Question id="71" level_id="1" type_id="1" subject_id="4" scrambled="true" chapter="">
        <Content></Content>
        <Answer correct="true"></Answer>
        <Answer correct="false"></Answer>
        <Answer correct="false"></Answer>
        <Answer correct="false"></Answer>
    </Question>
    
    <Question id="72" level_id="1" type_id="1" subject_id="4" scrambled="true" chapter="">
        <Content></Content>
        <Answer correct="true"></Answer>
        <Answer correct="false"></Answer>
        <Answer correct="false"></Answer>
        <Answer correct="false"></Answer>
    </Question>
    
    <Question id="73" level_id="1" type_id="1" subject_id="4" scrambled="true" chapter="">
        <Content></Content>
        <Answer correct="true"></Answer>
        <Answer correct="false"></Answer>
        <Answer correct="false"></Answer>
        <Answer correct="false"></Answer>
    </Question>
    
    <Question id="74" level_id="1" type_id="1" subject_id="4" scrambled="true" chapter="">
        <Content></Content>
        <Answer correct="true"></Answer>
        <Answer correct="false"></Answer>
        <Answer correct="false"></Answer>
        <Answer correct="false"></Answer>
    </Question>
    
    <Question id="75" level_id="1" type_id="1" subject_id="4" scrambled="true" chapter="">
        <Content></Content>
        <Answer correct="true"></Answer>
        <Answer correct="false"></Answer>
        <Answer correct="false"></Answer>
        <Answer correct="false"></Answer>
    </Question>
    
    <Question id="76" level_id="1" type_id="1" subject_id="4" scrambled="true" chapter="">
        <Content></Content>
        <Answer correct="true"></Answer>
        <Answer correct="false"></Answer>
        <Answer correct="false"></Answer>
        <Answer correct="false"></Answer>
    </Question>
    
    <Question id="77" level_id="1" type_id="1" subject_id="4" scrambled="true" chapter="">
        <Content></Content>
        <Answer correct="true"></Answer>
        <Answer correct="false"></Answer>
        <Answer correct="false"></Answer>
        <Answer correct="false"></Answer>
    </Question>
    
    <Question id="78" level_id="1" type_id="1" subject_id="4" scrambled="true" chapter="">
        <Content></Content>
        <Answer correct="true"></Answer>
        <Answer correct="false"></Answer>
        <Answer correct="false"></Answer>
        <Answer correct="false"></Answer>
    </Question>
    
    <Question id="79" level_id="1" type_id="1" subject_id="4" scrambled="true" chapter="">
        <Content></Content>
        <Answer correct="true"></Answer>
        <Answer correct="false"></Answer>
        <Answer correct="false"></Answer>
        <Answer correct="false"></Answer>
    </Question>
    
    <Question id="80" level_id="1" type_id="1" subject_id="4" scrambled="true" chapter="">
        <Content></Content>
        <Answer correct="true"></Answer>
        <Answer correct="false"></Answer>
        <Answer correct="false"></Answer>
        <Answer correct="false"></Answer>
    </Question>
    
    <Question id="81" level_id="1" type_id="1" subject_id="5" scrambled="true" chapter="">
        <Content>What does XML stand for?</Content>
        <Answer correct="true">eXtensible Markup Language</Answer>
        <Answer correct="false">Example Markup Language</Answer>
        <Answer correct="false">eXtra Modern Link</Answer>
        <Answer correct="false">X-Markup Language</Answer>
    </Question>
    
    <Question id="82" level_id="1" type_id="1" subject_id="5" scrambled="true" chapter="">
        <Content></Content>
        <Answer correct="true"></Answer>
        <Answer correct="false"></Answer>
        <Answer correct="false"></Answer>
        <Answer correct="false"></Answer>
    </Question>
    
    <Question id="83" level_id="1" type_id="1" subject_id="5" scrambled="true" chapter="">
        <Content></Content>
        <Answer correct="true"></Answer>
        <Answer correct="false"></Answer>
        <Answer correct="false"></Answer>
        <Answer correct="false"></Answer>
    </Question>
    
    <Question id="84" level_id="1" type_id="1" subject_id="5" scrambled="true" chapter="">
        <Content></Content>
        <Answer correct="true"></Answer>
        <Answer correct="false"></Answer>
        <Answer correct="false"></Answer>
        <Answer correct="false"></Answer>
    </Question>
    
    <Question id="85" level_id="1" type_id="1" subject_id="5" scrambled="true" chapter="">
        <Content></Content>
        <Answer correct="true"></Answer>
        <Answer correct="false"></Answer>
        <Answer correct="false"></Answer>
        <Answer correct="false"></Answer>
    </Question>
    
    <Question id="86" level_id="1" type_id="1" subject_id="5" scrambled="true" chapter="">
        <Content></Content>
        <Answer correct="true"></Answer>
        <Answer correct="false"></Answer>
        <Answer correct="false"></Answer>
        <Answer correct="false"></Answer>
    </Question>
    
    <Question id="87" level_id="1" type_id="1" subject_id="5" scrambled="true" chapter="">
        <Content></Content>
        <Answer correct="true"></Answer>
        <Answer correct="false"></Answer>
        <Answer correct="false"></Answer>
        <Answer correct="false"></Answer>
    </Question>
    
    <Question id="88" level_id="1" type_id="1" subject_id="5" scrambled="true" chapter="">
        <Content></Content>
        <Answer correct="true"></Answer>
        <Answer correct="false"></Answer>
        <Answer correct="false"></Answer>
        <Answer correct="false"></Answer>
    </Question>
    
    <Question id="89" level_id="1" type_id="1" subject_id="5" scrambled="true" chapter="">
        <Content></Content>
        <Answer correct="true"></Answer>
        <Answer correct="false"></Answer>
        <Answer correct="false"></Answer>
        <Answer correct="false"></Answer>
    </Question>
    
    <Question id="90" level_id="1" type_id="1" subject_id="5" scrambled="true" chapter="">
        <Content></Content>
        <Answer correct="true"></Answer>
        <Answer correct="false"></Answer>
        <Answer correct="false"></Answer>
        <Answer correct="false"></Answer>
    </Question>
    
    <Question id="91" level_id="1" type_id="1" subject_id="5" scrambled="true" chapter="">
        <Content></Content>
        <Answer correct="true"></Answer>
        <Answer correct="false"></Answer>
        <Answer correct="false"></Answer>
        <Answer correct="false"></Answer>
    </Question>
    
    <Question id="92" level_id="1" type_id="1" subject_id="5" scrambled="true" chapter="">
        <Content></Content>
        <Answer correct="true"></Answer>
        <Answer correct="false"></Answer>
        <Answer correct="false"></Answer>
        <Answer correct="false"></Answer>
    </Question>
    
    <Question id="93" level_id="1" type_id="1" subject_id="5" scrambled="true" chapter="">
        <Content></Content>
        <Answer correct="true"></Answer>
        <Answer correct="false"></Answer>
        <Answer correct="false"></Answer>
        <Answer correct="false"></Answer>
    </Question>
    
    <Question id="94" level_id="1" type_id="1" subject_id="5" scrambled="true" chapter="">
        <Content></Content>
        <Answer correct="true"></Answer>
        <Answer correct="false"></Answer>
        <Answer correct="false"></Answer>
        <Answer correct="false"></Answer>
    </Question>
    
    <Question id="95" level_id="1" type_id="1" subject_id="5" scrambled="true" chapter="">
        <Content></Content>
        <Answer correct="true"></Answer>
        <Answer correct="false"></Answer>
        <Answer correct="false"></Answer>
        <Answer correct="false"></Answer>
    </Question>
    
    <Question id="96" level_id="1" type_id="1" subject_id="5" scrambled="true" chapter="">
        <Content></Content>
        <Answer correct="true"></Answer>
        <Answer correct="false"></Answer>
        <Answer correct="false"></Answer>
        <Answer correct="false"></Answer>
    </Question>
    
    <Question id="97" level_id="1" type_id="1" subject_id="5" scrambled="true" chapter="">
        <Content></Content>
        <Answer correct="true"></Answer>
        <Answer correct="false"></Answer>
        <Answer correct="false"></Answer>
        <Answer correct="false"></Answer>
    </Question>
    
    <Question id="98" level_id="1" type_id="1" subject_id="5" scrambled="true" chapter="">
        <Content></Content>
        <Answer correct="true"></Answer>
        <Answer correct="false"></Answer>
        <Answer correct="false"></Answer>
        <Answer correct="false"></Answer>
    </Question>
    
    <Question id="99" level_id="1" type_id="1" subject_id="5" scrambled="true" chapter="">
        <Content></Content>
        <Answer correct="true"></Answer>
        <Answer correct="false"></Answer>
        <Answer correct="false"></Answer>
        <Answer correct="false"></Answer>
    </Question>
    
    <Question id="100" level_id="1" type_id="1" subject_id="5" scrambled="true" chapter="">
        <Content></Content>
        <Answer correct="true"></Answer>
        <Answer correct="false"></Answer>
        <Answer correct="false"></Answer>
        <Answer correct="false"></Answer>
    </Question>
    
    <Question id="101" level_id="1" type_id="1" subject_id="6" scrambled="true" chapter="">
        <Content></Content>
        <Answer correct="true"></Answer>
        <Answer correct="false"></Answer>
        <Answer correct="false"></Answer>
        <Answer correct="false"></Answer>
    </Question>
    
    <Question id="102" level_id="1" type_id="1" subject_id="6" scrambled="true" chapter="">
        <Content></Content>
        <Answer correct="true"></Answer>
        <Answer correct="false"></Answer>
        <Answer correct="false"></Answer>
        <Answer correct="false"></Answer>
    </Question>
    
    <Question id="103" level_id="1" type_id="1" subject_id="6" scrambled="true" chapter="">
        <Content></Content>
        <Answer correct="true"></Answer>
        <Answer correct="false"></Answer>
        <Answer correct="false"></Answer>
        <Answer correct="false"></Answer>
    </Question>
    
    <Question id="104" level_id="1" type_id="1" subject_id="6" scrambled="true" chapter="">
        <Content></Content>
        <Answer correct="true"></Answer>
        <Answer correct="false"></Answer>
        <Answer correct="false"></Answer>
        <Answer correct="false"></Answer>
    </Question>
    
    <Question id="105" level_id="1" type_id="1" subject_id="6" scrambled="true" chapter="">
        <Content></Content>
        <Answer correct="true"></Answer>
        <Answer correct="false"></Answer>
        <Answer correct="false"></Answer>
        <Answer correct="false"></Answer>
    </Question>
    
    <Question id="106" level_id="1" type_id="1" subject_id="6" scrambled="true" chapter="">
        <Content></Content>
        <Answer correct="true"></Answer>
        <Answer correct="false"></Answer>
        <Answer correct="false"></Answer>
        <Answer correct="false"></Answer>
    </Question>
    
    <Question id="107" level_id="1" type_id="1" subject_id="6" scrambled="true" chapter="">
        <Content></Content>
        <Answer correct="true"></Answer>
        <Answer correct="false"></Answer>
        <Answer correct="false"></Answer>
        <Answer correct="false"></Answer>
    </Question>
    
    <Question id="108" level_id="1" type_id="1" subject_id="6" scrambled="true" chapter="">
        <Content></Content>
        <Answer correct="true"></Answer>
        <Answer correct="false"></Answer>
        <Answer correct="false"></Answer>
        <Answer correct="false"></Answer>
    </Question>
    
    <Question id="109" level_id="1" type_id="1" subject_id="6" scrambled="true" chapter="">
        <Content></Content>
        <Answer correct="true"></Answer>
        <Answer correct="false"></Answer>
        <Answer correct="false"></Answer>
        <Answer correct="false"></Answer>
    </Question>
    
    <Question id="110" level_id="1" type_id="1" subject_id="6" scrambled="true" chapter="1">
        <Content>What does XML stand for?</Content>
        <Answer correct="true">eXtensible Markup Language</Answer>
        <Answer correct="false">X-Markup Language</Answer>
        <Answer correct="false">Example Markup Language</Answer>
        <Answer correct="false">eXtra Modern Link</Answer>
    </Question>
    
    <Question id="111" level_id="2" type_id="1" subject_id="6" scrambled="true" chapter="2">
        <Content>There is a way of describing XML data, how?</Content>
        <Answer correct="false">XML uses a description node to describe data</Answer>
        <Answer correct="true">XML uses a DTD to describe the data</Answer>
        <Answer correct="false">XML uses XSL to describe data</Answer>
    </Question>
    
    <Question id="112" level_id="3" type_id="1" subject_id="6" scrambled="true" chapter="3">
        <Content>XML's goal is to replace HTML</Content>
        <Answer correct="true">false</Answer>
        <Answer correct="false">true</Answer>
    </Question>
    
    <Question id="113" level_id="1" type_id="1" subject_id="6" scrambled="true" chapter="1">
        <Content>What is the correct syntax of the declaration which defines the XML version?</Content>
        <Answer correct="false">&lt; ? xml version=&quot;1.0&quot; /&gt;</Answer>
        <Answer correct="false">&lt; xml version=&quot;1.0&quot; /&gt;</Answer>
        <Answer correct="true">&lt; ?xml version=&quot;1.0&quot; ?&gt;</Answer>
    </Question>
    
    <Question id="114" level_id="2" type_id="1" subject_id="6" scrambled="true" chapter="5">
        <Content> What does DTD stand for?</Content>
        <Answer correct="false">Dynamic Type Definition</Answer>
        <Answer correct="false">Direct Type Definition</Answer>
        <Answer correct="true">Document Type Definition</Answer>
        <Answer correct="false">Do The Dance</Answer>
    </Question>
    
    <Question id="115" level_id="2" type_id="1" subject_id="6" scrambled="true" chapter="5">
        <Content>Which statement is true?</Content>
        <Answer correct="false">All XML elements must be lower case</Answer>
        <Answer correct="false">All the statements are true</Answer>
        <Answer correct="true">All XML elements must be properly closed</Answer>
        <Answer correct="false">All XML documents must have a DTD</Answer>
    </Question>
    
    <Question id="116" level_id="3" type_id="1" subject_id="6" scrambled="true" chapter="6">
        <Content> Which statement is true?</Content>
        <Answer correct="false">XML tags are case sensitive</Answer>
        <Answer correct="false">XML elements must be properly nested</Answer>
        <Answer correct="false">XML documents must have a root tag</Answer>
        <Answer correct="true">All the statements are true</Answer>
    </Question>
    
    <Question id="117" level_id="3" type_id="1" subject_id="6" scrambled="true" chapter="3">
        <Content>XML preserves white spaces</Content>
        <Answer correct="true">true</Answer>
        <Answer correct="false">false</Answer>
    </Question>

    <Question id="118" level_id="3" type_id="1" subject_id="6" scrambled="false" chapter="1">
        <Content>XML elements cannot be empty</Content>
        <Answer correct="true">false</Answer>
        <Answer correct="false">true</Answer>
    </Question>

    <Question id="119" level_id="3" type_id="1" subject_id="6" scrambled="true" chapter="5">
        <Content> XML attribute values must always be enclosed in quotes</Content>
        <Answer correct="true">true</Answer>
        <Answer correct="false">false</Answer>
    </Question>
    
    <Question id="120" level_id="1" type_id="1" subject_id="6" scrambled="true" chapter="6">
        <Content>What does XSL stand for?</Content>
        <Answer correct="false">eXpandable Style Language</Answer>
        <Answer correct="false">eXtra Style Language</Answer>
        <Answer correct="false">eXtensible Style Listing</Answer>
        <Answer correct="true">eXtensible Stylesheet Language</Answer>
    </Question>
</Questions>